tests/__init__.py
tests/test_component_types.py
tests/test_argparse.py
tests/test_component_instance_shortcuts.py
tests/test_func_invocation.py
banzai-0.0.dist-info/RECORD
banzai-0.0.dist-info/METADATA
banzai-0.0.dist-info/metadata.json
banzai-0.0.dist-info/WHEEL
banzai-0.0.dist-info/DESCRIPTION.rst
banzai-0.0.dist-info/top_level.txt
