Metadata-Version: 2.0
Name: banzai
Version: 0.0
Summary: Tool for pipelining tasks together through a CLI interface
Home-page: http://github.com/twneale/banzai/
Author: Thom Neale
Author-email: twneale@gmail.com
License: BSD
Platform: any
